[
  {
    "kind": "ClusterPlatformRoleBinding",
    "plural": "clusterplatformrolebindings",
    "group": "platform.enterprise.stacklok.com",
    "version": "v1alpha1",
    "shortNames": [
      "cprb",
      "clusterplatformrolebinding"
    ],
    "scope": "Cluster",
    "description": "ClusterPlatformRoleBinding binds ClusterPlatformRoles to principals cluster-wide.",
    "references": [
      {
        "targetKind": "ClusterPlatformRole",
        "paths": [
          "spec.bindings[].roleRef"
        ]
      }
    ],
    "referencedBy": [],
    "slug": "clusterplatformrolebinding"
  },
  {
    "kind": "ClusterPlatformRole",
    "plural": "clusterplatformroles",
    "group": "platform.enterprise.stacklok.com",
    "version": "v1alpha1",
    "shortNames": [
      "cpr",
      "clusterplatformrole"
    ],
    "scope": "Cluster",
    "description": "ClusterPlatformRole defines a named set of product actions that can be\nbound to principals via ToolhiveAuthorizationPolicy.",
    "references": [],
    "referencedBy": [
      {
        "sourceKind": "ClusterPlatformRoleBinding",
        "paths": [
          "spec.bindings[].roleRef"
        ]
      },
      {
        "sourceKind": "PlatformRoleBinding",
        "paths": [
          "spec.bindings[].roleRef"
        ]
      },
      {
        "sourceKind": "ToolhiveAuthorizationPolicy",
        "paths": [
          "spec.bindings[].roleRef"
        ]
      }
    ],
    "slug": "clusterplatformrole"
  },
  {
    "kind": "PlatformRoleBinding",
    "plural": "platformrolebindings",
    "group": "platform.enterprise.stacklok.com",
    "version": "v1alpha1",
    "shortNames": [
      "prb",
      "platformrolebinding"
    ],
    "scope": "Namespaced",
    "description": "PlatformRoleBinding binds ClusterPlatformRoles to principals within a namespace.",
    "references": [
      {
        "targetKind": "ClusterPlatformRole",
        "paths": [
          "spec.bindings[].roleRef"
        ]
      }
    ],
    "referencedBy": [],
    "slug": "platformrolebinding"
  },
  {
    "kind": "ToolhiveAuthorizationPolicy",
    "plural": "toolhiveauthorizationpolicies",
    "group": "toolhive.enterprise.stacklok.com",
    "version": "v1alpha1",
    "shortNames": [
      "tap",
      "authzpolicy"
    ],
    "scope": "Namespaced",
    "description": "ToolhiveAuthorizationPolicy defines authorization policy for an MCP server.",
    "references": [
      {
        "targetKind": "ClusterPlatformRole",
        "paths": [
          "spec.bindings[].roleRef"
        ]
      }
    ],
    "referencedBy": [],
    "slug": "toolhiveauthorizationpolicy"
  }
]
